README.rst
setup.py
py_pwned/__init__.py
py_pwned/pwned.py
py_pwned.egg-info/PKG-INFO
py_pwned.egg-info/SOURCES.txt
py_pwned.egg-info/dependency_links.txt
py_pwned.egg-info/not-zip-safe
py_pwned.egg-info/requires.txt
py_pwned.egg-info/top_level.txt