Metadata-Version: 1.1
Name: py-pwned
Version: 0.2
Summary: Python3 Have I been Pwned checker
Home-page: https://bitbucket.org/tvdsluijs/py_pwned
Author: Theo van der Sluijs
Author-email: theo@vandersluijs.nl
License: CC BY-NC-SA 4.0
Keywords: pwned hacked passwords email e-mail
Platform: UNKNOWN
Classifier: Programming Language :: Python :: 3
Classifier: Programming Language :: Python :: 3.3
Classifier: Programming Language :: Python :: 3.4
Classifier: Programming Language :: Python :: 3.5
